latex/__init__.py
latex/artifacts/table-2_1.tex
latex/artifacts/table-2_2.tex
latex/frog.jpg
latex/latex.py
latex/test.py
python_pro_latex_remaster-0.1.2.dist-info/METADATA
python_pro_latex_remaster-0.1.2.dist-info/WHEEL
python_pro_latex_remaster-0.1.2.dist-info/RECORD
