Metadata-Version: 2.1
Name: python-pro-latex-remaster
Version: 0.1.2
Summary: LaTeX helper functions for Python
Author: DanilMargaryan
Author-email: daniilmargaran31028@gmail.com
Requires-Python: >=3.7,<4.0
Classifier: Programming Language :: Python :: 3
Classifier: Programming Language :: Python :: 3.7
Classifier: Programming Language :: Python :: 3.8
Classifier: Programming Language :: Python :: 3.9
Classifier: Programming Language :: Python :: 3.10
Classifier: Programming Language :: Python :: 3.11
Requires-Dist: click (>=8.1.7,<9.0.0)
